CHANGES
LICENSE
MANIFEST.in
README.rst
setup.py
sphinxcontrib/__init__.py
sphinxcontrib/cf3domain.py
sphinxcontrib_cf3domain.egg-info/PKG-INFO
sphinxcontrib_cf3domain.egg-info/SOURCES.txt
sphinxcontrib_cf3domain.egg-info/dependency_links.txt
sphinxcontrib_cf3domain.egg-info/namespace_packages.txt
sphinxcontrib_cf3domain.egg-info/not-zip-safe
sphinxcontrib_cf3domain.egg-info/requires.txt
sphinxcontrib_cf3domain.egg-info/top_level.txt