Metadata-Version: 1.1
Name: sphinxcontrib-cf3domain
Version: 0.1
Summary: Sphinx domain for CFEngine 3 policies
Home-page: http://bitbucket.org/birkenfeld/sphinx-contrib
Author: Jimmy Thrasibule
Author-email: jimmy.thrasibule@gmail.com
License: BSD
Download-URL: http://pypi.python.org/pypi/sphinxcontrib-cf3domain
Keywords: sphinx cfengine
Platform: any
Classifier: Development Status :: 3 - Alpha
Classifier: Environment :: Console
Classifier: Intended Audience :: Developers
Classifier: Intended Audience :: Information Technology
Classifier: Intended Audience :: System Administrators
Classifier: License :: OSI Approved :: BSD License
Classifier: Operating System :: OS Independent
Classifier: Programming Language :: Python
Classifier: Topic :: Documentation
Classifier: Topic :: Documentation :: Sphinx
Classifier: Topic :: Text Processing :: Markup
Classifier: Topic :: Utilities
